{
  "AWSTemplateFormatVersion": "2010-09-09",
  "Description": "The AWS CloudFormation template for this Serverless application",
  "Resources": {
    "ServerlessDeploymentBucket": {
      "Type": "AWS::S3::Bucket",
      "Properties": {
        "BucketEncryption": {
          "ServerSideEncryptionConfiguration": [
            {
              "ServerSideEncryptionByDefault": {
                "SSEAlgorithm": "AES256"
              }
            }
          ]
        }
      }
    },
    "ServerlessDeploymentBucketPolicy": {
      "Type": "AWS::S3::BucketPolicy",
      "Properties": {
        "Bucket": {
          "Ref": "ServerlessDeploymentBucket"
        },
        "PolicyDocument": {
          "Statement": [
            {
              "Action": "s3:*",
              "Effect": "Deny",
              "Principal": "*",
              "Resource": [
                {
                  "Fn::Join": [
                    "",
                    [
                      "arn:",
                      {
                        "Ref": "AWS::Partition"
                      },
                      ":s3:::",
                      {
                        "Ref": "ServerlessDeploymentBucket"
                      },
                      "/*"
                    ]
                  ]
                },
                {
                  "Fn::Join": [
                    "",
                    [
                      "arn:",
                      {
                        "Ref": "AWS::Partition"
                      },
                      ":s3:::",
                      {
                        "Ref": "ServerlessDeploymentBucket"
                      }
                    ]
                  ]
                }
              ],
              "Condition": {
                "Bool": {
                  "aws:SecureTransport": false
                }
              }
            }
          ]
        }
      }
    },
    "MainLogGroup": {
      "Type": "AWS::Logs::LogGroup",
      "Properties": {
        "LogGroupName": "/aws/lambda/thricos-backend-dev-main"
      }
    },
    "IamRoleLambdaExecution": {
      "Type": "AWS::IAM::Role",
      "Properties": {
        "AssumeRolePolicyDocument": {
          "Version": "2012-10-17",
          "Statement": [
            {
              "Effect": "Allow",
              "Principal": {
                "Service": [
                  "lambda.amazonaws.com"
                ]
              },
              "Action": [
                "sts:AssumeRole"
              ]
            }
          ]
        },
        "Policies": [
          {
            "PolicyName": {
              "Fn::Join": [
                "-",
                [
                  "thricos-backend",
                  "dev",
                  "lambda"
                ]
              ]
            },
            "PolicyDocument": {
              "Version": "2012-10-17",
              "Statement": [
                {
                  "Effect": "Allow",
                  "Action": [
                    "logs:CreateLogStream",
                    "logs:CreateLogGroup",
                    "logs:TagResource"
                  ],
                  "Resource": [
                    {
                      "Fn::Sub": "arn:${AWS::Partition}:logs:${AWS::Region}:${AWS::AccountId}:log-group:/aws/lambda/thricos-backend-dev*:*"
                    }
                  ]
                },
                {
                  "Effect": "Allow",
                  "Action": [
                    "logs:PutLogEvents"
                  ],
                  "Resource": [
                    {
                      "Fn::Sub": "arn:${AWS::Partition}:logs:${AWS::Region}:${AWS::AccountId}:log-group:/aws/lambda/thricos-backend-dev*:*:*"
                    }
                  ]
                }
              ]
            }
          }
        ],
        "Path": "/",
        "RoleName": {
          "Fn::Join": [
            "-",
            [
              "thricos-backend",
              "dev",
              {
                "Ref": "AWS::Region"
              },
              "lambdaRole"
            ]
          ]
        }
      }
    },
    "MainLambdaFunction": {
      "Type": "AWS::Lambda::Function",
      "Properties": {
        "Code": {
          "S3Bucket": {
            "Ref": "ServerlessDeploymentBucket"
          },
          "S3Key": "serverless/thricos-backend/dev/1678561721615-2023-03-11T19:08:41.615Z/thricos-backend.zip"
        },
        "Handler": "dist/serverless.handler",
        "Runtime": "nodejs16.x",
        "FunctionName": "thricos-backend-dev-main",
        "MemorySize": 1024,
        "Timeout": 20,
        "Environment": {
          "Variables": {
            "TOKEN_KEY": "asdl/12#dqz-dqwd",
            "DATABASE_URL": "postgresql://admin_thricos:Kunkka_1610@thricos-marketplace-database.c423ehsvjvmb.eu-west-1.rds.amazonaws.com:5432/postgres?connection_timeout=500&sslmode=disable",
            "CLIENT_ID": "1053079554666-265tipmhgv7oqf5kg24mgonn65ujrbi0.apps.googleusercontent.com",
            "CLIENT_SECRET": "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",
            "CALLBACK_URL": "http://localhost:8080/api/v1/auth/google/callback"
          }
        },
        "Role": {
          "Fn::GetAtt": [
            "IamRoleLambdaExecution",
            "Arn"
          ]
        },
        "Layers": [
          "arn:aws:lambda:eu-west-1:683323173810:layer:node_module_thricos_first:6",
          "arn:aws:lambda:eu-west-1:683323173810:layer:node_module_thricos_second:5"
        ]
      },
      "DependsOn": [
        "MainLogGroup"
      ]
    },
    "MainLambdaVersionGH45vtyhAohnvWsZYYWRoXKjopwXaSgTn8BzP3KiSY": {
      "Type": "AWS::Lambda::Version",
      "DeletionPolicy": "Retain",
      "Properties": {
        "FunctionName": {
          "Ref": "MainLambdaFunction"
        },
        "CodeSha256": "msTNcnH8EGhmdtVPtQHmc3FQTIBUpj+Yrc7NBr6wqE8="
      }
    },
    "ApiGatewayRestApi": {
      "Type": "AWS::ApiGateway::RestApi",
      "Properties": {
        "Name": "dev-thricos-backend",
        "EndpointConfiguration": {
          "Types": [
            "EDGE"
          ]
        },
        "Policy": ""
      }
    },
    "ApiGatewayResourceProxyVar": {
      "Type": "AWS::ApiGateway::Resource",
      "Properties": {
        "ParentId": {
          "Fn::GetAtt": [
            "ApiGatewayRestApi",
            "RootResourceId"
          ]
        },
        "PathPart": "{proxy+}",
        "RestApiId": {
          "Ref": "ApiGatewayRestApi"
        }
      }
    },
    "ApiGatewayMethodOptions": {
      "Type": "AWS::ApiGateway::Method",
      "Properties": {
        "AuthorizationType": "NONE",
        "HttpMethod": "OPTIONS",
        "MethodResponses": [
          {
            "StatusCode": "200",
            "ResponseParameters": {
              "method.response.header.Access-Control-Allow-Origin": true,
              "method.response.header.Access-Control-Allow-Headers": true,
              "method.response.header.Access-Control-Allow-Methods": true
            },
            "ResponseModels": {}
          }
        ],
        "RequestParameters": {},
        "Integration": {
          "Type": "MOCK",
          "RequestTemplates": {
            "application/json": "{statusCode:200}"
          },
          "ContentHandling": "CONVERT_TO_TEXT",
          "IntegrationResponses": [
            {
              "StatusCode": "200",
              "ResponseParameters": {
                "method.response.header.Access-Control-Allow-Origin": "'*'",
                "method.response.header.Access-Control-Allow-Headers": "'Content-Type,X-Amz-Date,Authorization,X-Api-Key,X-Amz-Security-Token,X-Amz-User-Agent'",
                "method.response.header.Access-Control-Allow-Methods": "'OPTIONS,DELETE,GET,HEAD,PATCH,POST,PUT'"
              },
              "ResponseTemplates": {
                "application/json": ""
              }
            }
          ]
        },
        "ResourceId": {
          "Fn::GetAtt": [
            "ApiGatewayRestApi",
            "RootResourceId"
          ]
        },
        "RestApiId": {
          "Ref": "ApiGatewayRestApi"
        }
      }
    },
    "ApiGatewayMethodProxyVarOptions": {
      "Type": "AWS::ApiGateway::Method",
      "Properties": {
        "AuthorizationType": "NONE",
        "HttpMethod": "OPTIONS",
        "MethodResponses": [
          {
            "StatusCode": "200",
            "ResponseParameters": {
              "method.response.header.Access-Control-Allow-Origin": true,
              "method.response.header.Access-Control-Allow-Headers": true,
              "method.response.header.Access-Control-Allow-Methods": true
            },
            "ResponseModels": {}
          }
        ],
        "RequestParameters": {},
        "Integration": {
          "Type": "MOCK",
          "RequestTemplates": {
            "application/json": "{statusCode:200}"
          },
          "ContentHandling": "CONVERT_TO_TEXT",
          "IntegrationResponses": [
            {
              "StatusCode": "200",
              "ResponseParameters": {
                "method.response.header.Access-Control-Allow-Origin": "'*'",
                "method.response.header.Access-Control-Allow-Headers": "'Content-Type,X-Amz-Date,Authorization,X-Api-Key,X-Amz-Security-Token,X-Amz-User-Agent'",
                "method.response.header.Access-Control-Allow-Methods": "'OPTIONS,DELETE,GET,HEAD,PATCH,POST,PUT'"
              },
              "ResponseTemplates": {
                "application/json": ""
              }
            }
          ]
        },
        "ResourceId": {
          "Ref": "ApiGatewayResourceProxyVar"
        },
        "RestApiId": {
          "Ref": "ApiGatewayRestApi"
        }
      }
    },
    "ApiGatewayMethodAny": {
      "Type": "AWS::ApiGateway::Method",
      "Properties": {
        "HttpMethod": "ANY",
        "RequestParameters": {},
        "ResourceId": {
          "Fn::GetAtt": [
            "ApiGatewayRestApi",
            "RootResourceId"
          ]
        },
        "RestApiId": {
          "Ref": "ApiGatewayRestApi"
        },
        "ApiKeyRequired": false,
        "AuthorizationType": "NONE",
        "Integration": {
          "IntegrationHttpMethod": "POST",
          "Type": "AWS_PROXY",
          "Uri": {
            "Fn::Join": [
              "",
              [
                "arn:",
                {
                  "Ref": "AWS::Partition"
                },
                ":apigateway:",
                {
                  "Ref": "AWS::Region"
                },
                ":lambda:path/2015-03-31/functions/",
                {
                  "Fn::GetAtt": [
                    "MainLambdaFunction",
                    "Arn"
                  ]
                },
                "/invocations"
              ]
            ]
          }
        },
        "MethodResponses": []
      },
      "DependsOn": [
        "MainLambdaPermissionApiGateway"
      ]
    },
    "ApiGatewayMethodProxyVarAny": {
      "Type": "AWS::ApiGateway::Method",
      "Properties": {
        "HttpMethod": "ANY",
        "RequestParameters": {},
        "ResourceId": {
          "Ref": "ApiGatewayResourceProxyVar"
        },
        "RestApiId": {
          "Ref": "ApiGatewayRestApi"
        },
        "ApiKeyRequired": false,
        "AuthorizationType": "NONE",
        "Integration": {
          "IntegrationHttpMethod": "POST",
          "Type": "AWS_PROXY",
          "Uri": {
            "Fn::Join": [
              "",
              [
                "arn:",
                {
                  "Ref": "AWS::Partition"
                },
                ":apigateway:",
                {
                  "Ref": "AWS::Region"
                },
                ":lambda:path/2015-03-31/functions/",
                {
                  "Fn::GetAtt": [
                    "MainLambdaFunction",
                    "Arn"
                  ]
                },
                "/invocations"
              ]
            ]
          }
        },
        "MethodResponses": []
      },
      "DependsOn": [
        "MainLambdaPermissionApiGateway"
      ]
    },
    "ApiGatewayDeployment1678561702158": {
      "Type": "AWS::ApiGateway::Deployment",
      "Properties": {
        "RestApiId": {
          "Ref": "ApiGatewayRestApi"
        },
        "StageName": "dev"
      },
      "DependsOn": [
        "ApiGatewayMethodOptions",
        "ApiGatewayMethodProxyVarOptions",
        "ApiGatewayMethodAny",
        "ApiGatewayMethodProxyVarAny"
      ]
    },
    "MainLambdaPermissionApiGateway": {
      "Type": "AWS::Lambda::Permission",
      "Properties": {
        "FunctionName": {
          "Fn::GetAtt": [
            "MainLambdaFunction",
            "Arn"
          ]
        },
        "Action": "lambda:InvokeFunction",
        "Principal": "apigateway.amazonaws.com",
        "SourceArn": {
          "Fn::Join": [
            "",
            [
              "arn:",
              {
                "Ref": "AWS::Partition"
              },
              ":execute-api:",
              {
                "Ref": "AWS::Region"
              },
              ":",
              {
                "Ref": "AWS::AccountId"
              },
              ":",
              {
                "Ref": "ApiGatewayRestApi"
              },
              "/*/*"
            ]
          ]
        }
      }
    }
  },
  "Outputs": {
    "ServerlessDeploymentBucketName": {
      "Value": {
        "Ref": "ServerlessDeploymentBucket"
      },
      "Export": {
        "Name": "sls-thricos-backend-dev-ServerlessDeploymentBucketName"
      }
    },
    "MainLambdaFunctionQualifiedArn": {
      "Description": "Current Lambda function version",
      "Value": {
        "Ref": "MainLambdaVersionGH45vtyhAohnvWsZYYWRoXKjopwXaSgTn8BzP3KiSY"
      },
      "Export": {
        "Name": "sls-thricos-backend-dev-MainLambdaFunctionQualifiedArn"
      }
    },
    "ServiceEndpoint": {
      "Description": "URL of the service endpoint",
      "Value": {
        "Fn::Join": [
          "",
          [
            "https://",
            {
              "Ref": "ApiGatewayRestApi"
            },
            ".execute-api.",
            {
              "Ref": "AWS::Region"
            },
            ".",
            {
              "Ref": "AWS::URLSuffix"
            },
            "/dev"
          ]
        ]
      },
      "Export": {
        "Name": "sls-thricos-backend-dev-ServiceEndpoint"
      }
    }
  }
}